README.md
setup-unfair.py
setup.py
fairseq/__init__.py
fairseq/bleu.py
fairseq/distributed_utils.py
fairseq/legacy_distributed_data_parallel.py
fairseq/meters.py
fairseq/multiprocessing_pdb.py
fairseq/options.py
fairseq/progress_bar.py
fairseq/search.py
fairseq/sequence_generator.py
fairseq/sequence_scorer.py
fairseq/tokenizer.py
fairseq/trainer.py
fairseq/utils.py
fairseq/clib/libbleu/libbleu.cpp
fairseq/clib/libbleu/module.cpp
fairseq/criterions/__init__.py
fairseq/criterions/adaptive_loss.py
fairseq/criterions/composite_loss.py
fairseq/criterions/cross_entropy.py
fairseq/criterions/fairseq_criterion.py
fairseq/criterions/label_smoothed_cross_entropy.py
fairseq/data/__init__.py
fairseq/data/backtranslation_dataset.py
fairseq/data/concat_dataset.py
fairseq/data/data_utils.py
fairseq/data/dictionary.py
fairseq/data/fairseq_dataset.py
fairseq/data/indexed_dataset.py
fairseq/data/iterators.py
fairseq/data/language_pair_dataset.py
fairseq/data/monolingual_dataset.py
fairseq/data/noising.py
fairseq/data/round_robin_zip_datasets.py
fairseq/data/token_block_dataset.py
fairseq/data/transform_eos_dataset.py
fairseq/models/__init__.py
fairseq/models/composite_encoder.py
fairseq/models/distributed_fairseq_model.py
fairseq/models/fairseq_decoder.py
fairseq/models/fairseq_encoder.py
fairseq/models/fairseq_incremental_decoder.py
fairseq/models/fairseq_model.py
fairseq/models/fconv.py
fairseq/models/fconv_self_att.py
fairseq/models/lstm.py
fairseq/models/multilingual_transformer.py
fairseq/models/transformer.py
fairseq/modules/__init__.py
fairseq/modules/adaptive_input.py
fairseq/modules/adaptive_softmax.py
fairseq/modules/beamable_mm.py
fairseq/modules/character_token_embedder.py
fairseq/modules/conv_tbc.py
fairseq/modules/downsampled_multihead_attention.py
fairseq/modules/grad_multiply.py
fairseq/modules/highway.py
fairseq/modules/learned_positional_embedding.py
fairseq/modules/linearized_convolution.py
fairseq/modules/multihead_attention.py
fairseq/modules/scalar_bias.py
unfairseq.egg-info/PKG-INFO
unfairseq.egg-info/SOURCES.txt
unfairseq.egg-info/dependency_links.txt
unfairseq.egg-info/requires.txt
unfairseq.egg-info/top_level.txt