Metadata-Version: 1.0
Name: unfairseq
Version: 0.6.0.3
Summary: Unofficial Pacakge of Facebook AI Research Sequence-to-Sequence Toolkit
Home-page: UNKNOWN
Author: UNKNOWN
Author-email: UNKNOWN
License: BSD License
